txfixtures/__init__.py
txfixtures/osutils.py
txfixtures/reactor.py
txfixtures/service.py
txfixtures/tachandler.py
txfixtures/_twisted/__init__.py
txfixtures/_twisted/testing.py
txfixtures/_twisted/threading.py
txfixtures/_twisted/backports/__init__.py
txfixtures/_twisted/backports/defer.py
txfixtures/_twisted/backports/testing.py
txfixtures/_twisted/tests/__init__.py
txfixtures/_twisted/tests/test_threading.py
txfixtures/tests/__init__.py
txfixtures/tests/test_osutils.py
txfixtures/tests/test_reactor.py
txfixtures/tests/test_service.py
txfixtures-0.5.2.dist-info/AUTHORS
txfixtures-0.5.2.dist-info/METADATA
txfixtures-0.5.2.dist-info/WHEEL
txfixtures-0.5.2.dist-info/pbr.json
txfixtures-0.5.2.dist-info/top_level.txt
txfixtures-0.5.2.dist-info/RECORD
